costly/__init__.py
costly/costlog.py
costly/decorator.py
costly/updatable_default.py
costly/utils.py
costly/estimators/__init__.py
costly/estimators/llm_api_estimation.py
costly/simulators/__init__.py
costly/simulators/llm_simulator_faker.py
costly-2.3.7.dist-info/METADATA
costly-2.3.7.dist-info/WHEEL
costly-2.3.7.dist-info/licenses/LICENSE
costly-2.3.7.dist-info/RECORD
