Metadata-Version: 2.4
Name: costly
Version: 2.3.7
Summary: Estimate costs and running times of complex LLM workflows/experiments/pipelines in advance before spending money, via simulations.
Author-email: abhimanyu <abhimanyupallavisudhir@gmail.com>
License-File: LICENSE
Requires-Python: <4,>=3.11
Requires-Dist: faker<29,>=28.0.0
Requires-Dist: instructor>=1.4.2
Requires-Dist: jsonlines<5,>=4.0.0
Requires-Dist: litellm<2,>=1.59.6
Requires-Dist: openai<2,>=1.45.1
Requires-Dist: pydantic<3,>=2.8.2
Requires-Dist: pytest-asyncio<0.24,>=0.23.7
Requires-Dist: pytest-env<2,>=1.1.3
Requires-Dist: pytest-mock<4,>=3.14.0
Requires-Dist: pytest<9,>=8.1.1
Requires-Dist: python-dotenv
Requires-Dist: tiktoken<0.8,>=0.7.0
Requires-Dist: typing-extensions<5,>=4.12.2
